pyamifex/__init__.py
pyamifex/configkey.py
pyamifex/filedatamod.py
pyamifex/filelistmod.py
pyamifex/ifheadmod.py
pyamifex/ifjobmod.py
pyamifex/iflinemod.py
pyamifex/pyamifex.py
pyamifex/pyamifexlite.py
pyamifex/reconfilemod.py
pyamifex-0.9.6.dist-info/DESCRIPTION.rst
pyamifex-0.9.6.dist-info/METADATA
pyamifex-0.9.6.dist-info/RECORD
pyamifex-0.9.6.dist-info/WHEEL
pyamifex-0.9.6.dist-info/metadata.json
pyamifex-0.9.6.dist-info/top_level.txt
