Metadata-Version: 2.0
Name: pyamifex
Version: 0.9.6
Summary: UNKNOWN
Home-page: UNKNOWN
Author: qiqi
Author-email: qiqi@netsdl.com
License: Apache
Platform: UNKNOWN
Requires-Dist: SQLAlchemy (>=0.98)
Requires-Dist: XlsxWriter (>=1.0.2)
Requires-Dist: pyodbc (>=3.0.0)
Requires-Dist: xlrd (>=1.0.0)
Requires-Dist: xlutils (>=2.0.0)
Requires-Dist: xlwt (>=1.2.0)
